<?xml version="1.0" encoding="UTF-8"?>
<mxfile host="app.diagrams.net" agent="Mozilla/5.0 (Windows NT 10.0; Win64; x64) AppleWebKit/537.36 (KHTML, like Gecko) Chrome/145.0.0.0 Safari/537.36 Edg/145.0.0.0" version="29.4.0">
  <diagram name="Страница-1" id="2J4VqCRyF2botctCl09B">
    <mxGraphModel dx="978" dy="543" grid="1" gridSize="10" guides="1" tooltips="1" connect="1" arrows="1" fold="1" page="1" pageScale="1" pageWidth="827" pageHeight="1169" math="0" shadow="0">
      <root>
        <mxCell id="0" />
        <mxCell id="1" parent="0" />
        <mxCell id="ulpl8gQw-uzFRpP4TgdU-28" edge="1" parent="1" source="ulpl8gQw-uzFRpP4TgdU-1" style="edgeStyle=orthogonalEdgeStyle;rounded=0;orthogonalLoop=1;jettySize=auto;html=1;endArrow=none;endFill=0;endSize=8;startArrow=diamondThin;startFill=0;startSize=20;">
          <mxGeometry relative="1" as="geometry">
            <mxPoint x="440" y="445" as="targetPoint" />
          </mxGeometry>
        </mxCell>
        <mxCell id="ulpl8gQw-uzFRpP4TgdU-1" parent="1" style="swimlane;fontStyle=1;align=center;verticalAlign=top;childLayout=stackLayout;horizontal=1;startSize=30;horizontalStack=0;resizeParent=1;resizeParentMax=0;resizeLast=0;collapsible=1;marginBottom=0;whiteSpace=wrap;html=1;" value="Client" vertex="1">
          <mxGeometry height="30" width="140" x="210" y="430" as="geometry" />
        </mxCell>
        <mxCell id="ulpl8gQw-uzFRpP4TgdU-26" edge="1" parent="1" source="ulpl8gQw-uzFRpP4TgdU-5" style="edgeStyle=orthogonalEdgeStyle;rounded=0;orthogonalLoop=1;jettySize=auto;html=1;endArrow=none;endFill=0;endSize=8;" target="ulpl8gQw-uzFRpP4TgdU-21">
          <mxGeometry relative="1" as="geometry" />
        </mxCell>
        <mxCell id="ulpl8gQw-uzFRpP4TgdU-5" parent="1" style="swimlane;fontStyle=1;align=center;verticalAlign=top;childLayout=stackLayout;horizontal=1;startSize=26;horizontalStack=0;resizeParent=1;resizeParentMax=0;resizeLast=0;collapsible=1;marginBottom=0;whiteSpace=wrap;html=1;" value="Singleton" vertex="1">
          <mxGeometry height="110" width="160" x="440" y="230" as="geometry" />
        </mxCell>
        <mxCell id="ulpl8gQw-uzFRpP4TgdU-6" parent="ulpl8gQw-uzFRpP4TgdU-5" style="text;strokeColor=none;fillColor=none;align=left;verticalAlign=top;spacingLeft=4;spacingRight=4;overflow=hidden;rotatable=0;points=[[0,0.5],[1,0.5]];portConstraint=eastwest;whiteSpace=wrap;html=1;" value="&lt;u&gt;- Instance: Singleton&lt;/u&gt;" vertex="1">
          <mxGeometry height="26" width="160" y="26" as="geometry" />
        </mxCell>
        <mxCell id="ulpl8gQw-uzFRpP4TgdU-7" parent="ulpl8gQw-uzFRpP4TgdU-5" style="line;strokeWidth=1;fillColor=none;align=left;verticalAlign=middle;spacingTop=-1;spacingLeft=3;spacingRight=3;rotatable=0;labelPosition=right;points=[];portConstraint=eastwest;strokeColor=inherit;" value="" vertex="1">
          <mxGeometry height="8" width="160" y="52" as="geometry" />
        </mxCell>
        <mxCell id="ulpl8gQw-uzFRpP4TgdU-8" parent="ulpl8gQw-uzFRpP4TgdU-5" style="text;strokeColor=none;fillColor=none;align=left;verticalAlign=top;spacingLeft=4;spacingRight=4;overflow=hidden;rotatable=0;points=[[0,0.5],[1,0.5]];portConstraint=eastwest;whiteSpace=wrap;html=1;" value="- Singleton():&lt;div&gt;&lt;u&gt;+getInstance(): Singleton&lt;/u&gt;&lt;/div&gt;" vertex="1">
          <mxGeometry height="50" width="160" y="60" as="geometry" />
        </mxCell>
        <mxCell id="ulpl8gQw-uzFRpP4TgdU-25" edge="1" parent="1" source="ulpl8gQw-uzFRpP4TgdU-17" style="edgeStyle=orthogonalEdgeStyle;rounded=0;orthogonalLoop=1;jettySize=auto;html=1;endArrow=none;endFill=0;endSize=8;" target="ulpl8gQw-uzFRpP4TgdU-5">
          <mxGeometry relative="1" as="geometry" />
        </mxCell>
        <mxCell id="ulpl8gQw-uzFRpP4TgdU-17" parent="1" style="swimlane;fontStyle=1;align=center;verticalAlign=top;childLayout=stackLayout;horizontal=1;startSize=26;horizontalStack=0;resizeParent=1;resizeParentMax=0;resizeLast=0;collapsible=1;marginBottom=0;whiteSpace=wrap;html=1;" value="Queue" vertex="1">
          <mxGeometry height="84" width="160" x="200" y="243" as="geometry" />
        </mxCell>
        <mxCell id="ulpl8gQw-uzFRpP4TgdU-18" parent="ulpl8gQw-uzFRpP4TgdU-17" style="text;strokeColor=none;fillColor=none;align=left;verticalAlign=top;spacingLeft=4;spacingRight=4;overflow=hidden;rotatable=0;points=[[0,0.5],[1,0.5]];portConstraint=eastwest;whiteSpace=wrap;html=1;" value="&lt;div&gt;+ count: Integer&lt;/div&gt;" vertex="1">
          <mxGeometry height="24" width="160" y="26" as="geometry" />
        </mxCell>
        <mxCell id="ulpl8gQw-uzFRpP4TgdU-19" parent="ulpl8gQw-uzFRpP4TgdU-17" style="line;strokeWidth=1;fillColor=none;align=left;verticalAlign=middle;spacingTop=-1;spacingLeft=3;spacingRight=3;rotatable=0;labelPosition=right;points=[];portConstraint=eastwest;strokeColor=inherit;" value="" vertex="1">
          <mxGeometry height="8" width="160" y="50" as="geometry" />
        </mxCell>
        <mxCell id="ulpl8gQw-uzFRpP4TgdU-20" parent="ulpl8gQw-uzFRpP4TgdU-17" style="text;strokeColor=none;fillColor=none;align=left;verticalAlign=top;spacingLeft=4;spacingRight=4;overflow=hidden;rotatable=0;points=[[0,0.5],[1,0.5]];portConstraint=eastwest;whiteSpace=wrap;html=1;" value="+ method(type): type" vertex="1">
          <mxGeometry height="26" width="160" y="58" as="geometry" />
        </mxCell>
        <mxCell id="ulpl8gQw-uzFRpP4TgdU-21" parent="1" style="swimlane;fontStyle=1;align=center;verticalAlign=top;childLayout=stackLayout;horizontal=1;startSize=26;horizontalStack=0;resizeParent=1;resizeParentMax=0;resizeLast=0;collapsible=1;marginBottom=0;whiteSpace=wrap;html=1;" value="Worker" vertex="1">
          <mxGeometry height="86" width="160" x="440" y="390" as="geometry" />
        </mxCell>
        <mxCell id="ulpl8gQw-uzFRpP4TgdU-22" parent="ulpl8gQw-uzFRpP4TgdU-21" style="text;strokeColor=none;fillColor=none;align=left;verticalAlign=top;spacingLeft=4;spacingRight=4;overflow=hidden;rotatable=0;points=[[0,0.5],[1,0.5]];portConstraint=eastwest;whiteSpace=wrap;html=1;" value="+ field: type" vertex="1">
          <mxGeometry height="26" width="160" y="26" as="geometry" />
        </mxCell>
        <mxCell id="ulpl8gQw-uzFRpP4TgdU-23" parent="ulpl8gQw-uzFRpP4TgdU-21" style="line;strokeWidth=1;fillColor=none;align=left;verticalAlign=middle;spacingTop=-1;spacingLeft=3;spacingRight=3;rotatable=0;labelPosition=right;points=[];portConstraint=eastwest;strokeColor=inherit;" value="" vertex="1">
          <mxGeometry height="8" width="160" y="52" as="geometry" />
        </mxCell>
        <mxCell id="ulpl8gQw-uzFRpP4TgdU-24" parent="ulpl8gQw-uzFRpP4TgdU-21" style="text;strokeColor=none;fillColor=none;align=left;verticalAlign=top;spacingLeft=4;spacingRight=4;overflow=hidden;rotatable=0;points=[[0,0.5],[1,0.5]];portConstraint=eastwest;whiteSpace=wrap;html=1;" value="+ method(type): type" vertex="1">
          <mxGeometry height="26" width="160" y="60" as="geometry" />
        </mxCell>
        <mxCell id="ulpl8gQw-uzFRpP4TgdU-27" edge="1" parent="1" source="ulpl8gQw-uzFRpP4TgdU-1" style="edgeStyle=orthogonalEdgeStyle;rounded=0;orthogonalLoop=1;jettySize=auto;html=1;entryX=0.5;entryY=0.987;entryDx=0;entryDy=0;entryPerimeter=0;endArrow=none;endFill=0;endSize=8;startArrow=diamondThin;startFill=0;startSize=20;" target="ulpl8gQw-uzFRpP4TgdU-20">
          <mxGeometry relative="1" as="geometry" />
        </mxCell>
        <mxCell id="ulpl8gQw-uzFRpP4TgdU-30" parent="1" style="text;html=1;whiteSpace=wrap;strokeColor=none;fillColor=none;align=center;verticalAlign=middle;rounded=0;" value="+ queues" vertex="1">
          <mxGeometry height="30" width="60" x="280" y="327" as="geometry" />
        </mxCell>
        <mxCell id="ulpl8gQw-uzFRpP4TgdU-31" parent="1" style="text;html=1;whiteSpace=wrap;strokeColor=none;fillColor=none;align=center;verticalAlign=middle;rounded=0;" value="+ workers" vertex="1">
          <mxGeometry height="30" width="60" x="380" y="446" as="geometry" />
        </mxCell>
        <mxCell id="ulpl8gQw-uzFRpP4TgdU-32" parent="1" style="swimlane;fontStyle=1;align=center;verticalAlign=top;childLayout=stackLayout;horizontal=1;startSize=43;horizontalStack=0;resizeParent=1;resizeParentMax=0;resizeLast=0;collapsible=1;marginBottom=0;whiteSpace=wrap;html=1;" value="Task" vertex="1">
          <mxGeometry height="30" width="110" x="30" y="263" as="geometry" />
        </mxCell>
        <mxCell id="ulpl8gQw-uzFRpP4TgdU-36" edge="1" parent="1" source="ulpl8gQw-uzFRpP4TgdU-18" style="edgeStyle=orthogonalEdgeStyle;rounded=0;orthogonalLoop=1;jettySize=auto;html=1;endArrow=none;endFill=0;startArrow=diamondThin;startFill=1;startSize=20;">
          <mxGeometry relative="1" as="geometry">
            <Array as="points">
              <mxPoint x="170" y="281" />
              <mxPoint x="140" y="280" />
            </Array>
            <mxPoint x="140" y="280" as="targetPoint" />
          </mxGeometry>
        </mxCell>
        <mxCell id="ulpl8gQw-uzFRpP4TgdU-37" parent="1" style="text;html=1;whiteSpace=wrap;strokeColor=none;fillColor=none;align=center;verticalAlign=middle;rounded=0;" value="*" vertex="1">
          <mxGeometry height="30" width="60" x="340" y="263" as="geometry" />
        </mxCell>
        <mxCell id="ulpl8gQw-uzFRpP4TgdU-38" parent="1" style="text;html=1;whiteSpace=wrap;strokeColor=none;fillColor=none;align=center;verticalAlign=middle;rounded=0;" value="*" vertex="1">
          <mxGeometry height="30" width="60" x="500" y="370" as="geometry" />
        </mxCell>
        <mxCell id="ulpl8gQw-uzFRpP4TgdU-39" parent="1" style="text;html=1;whiteSpace=wrap;strokeColor=none;fillColor=none;align=center;verticalAlign=middle;rounded=0;" value="1" vertex="1">
          <mxGeometry height="30" width="60" x="400" y="260" as="geometry" />
        </mxCell>
        <mxCell id="ulpl8gQw-uzFRpP4TgdU-40" parent="1" style="text;html=1;whiteSpace=wrap;strokeColor=none;fillColor=none;align=center;verticalAlign=middle;rounded=0;" value="1" vertex="1">
          <mxGeometry height="30" width="60" x="500" y="340" as="geometry" />
        </mxCell>
      </root>
    </mxGraphModel>
  </diagram>
</mxfile>
